{
	"credit": "Made for Realism Mats Texture Pack",
	"textures": {
		"0": "block/weathered_copper_texture",
		"1": "block/weathered_copper_trapdoor",
		"particle": "block/weathered_copper_texture"
	},
	"elements": [
		{
			"from": [15, 0, 1],
			"to": [16, 2, 15],
			"rotation": {"angle": 0, "axis": "y", "origin": [8, 9, 8]},
			"faces": {
				"north": {"uv": [0, 0, 1, 2], "texture": "#0"},
				"east": {"uv": [1.798, 0, 4.36025, 15.985], "rotation": 90, "texture": "#0"},
				"south": {"uv": [0, 0, 1, 2], "texture": "#0"},
				"west": {"uv": [1.798, 0, 4.17275, 15.985], "rotation": 90, "texture": "#0"},
				"up": {"uv": [12.18738, 0, 13.73425, 15.985], "texture": "#0"},
				"down": {"uv": [8.28112, 0, 9.59362, 15.985], "texture": "#0"}
			}
		},
		{
			"from": [0, 0, 1],
			"to": [1, 2, 15],
			"rotation": {"angle": 0, "axis": "y", "origin": [-7, 9, 8]},
			"faces": {
				"north": {"uv": [0, 0, 1, 2], "texture": "#0"},
				"east": {"uv": [1.798, 0, 3.93838, 15.985], "rotation": 90, "texture": "#0"},
				"south": {"uv": [0, 0, 1, 2], "texture": "#0"},
				"west": {"uv": [1.798, 0, 3.79775, 15.985], "rotation": 90, "texture": "#0"},
				"up": {"uv": [7.73425, 0, 9.328, 15.985], "texture": "#0"},
				"down": {"uv": [4.6405, 0.015, 5.953, 16], "texture": "#0"}
			}
		},
		{
			"from": [0, 0, 0],
			"to": [16, 2, 1],
			"rotation": {"angle": 0, "axis": "y", "origin": [8, 9, 8]},
			"faces": {
				"north": {"uv": [1.798, 0, 3.454, 15.985], "rotation": 90, "texture": "#0"},
				"east": {"uv": [0.063, 0, 2.42213, 1.0475], "rotation": 90, "texture": "#0"},
				"south": {"uv": [0.82925, 0, 3.454, 15.985], "rotation": 90, "texture": "#0"},
				"west": {"uv": [0.063, 0, 2.469, 1.09437], "rotation": 90, "texture": "#0"},
				"up": {"uv": [4.34363, 0.015, 5.71863, 16], "rotation": 90, "texture": "#0"},
				"down": {"uv": [5.828, 0, 7.1405, 15.985], "rotation": 90, "texture": "#0"}
			}
		},
		{
			"from": [0, 0, 15],
			"to": [16, 2, 16],
			"rotation": {"angle": 0, "axis": "y", "origin": [8, 9, 23]},
			"faces": {
				"north": {"uv": [1.798, 0, 3.454, 15.985], "rotation": 90, "texture": "#0"},
				"east": {"uv": [0.063, 0, 2.42213, 1.0475], "rotation": 90, "texture": "#0"},
				"south": {"uv": [0.82925, 0, 3.454, 15.985], "rotation": 90, "texture": "#0"},
				"west": {"uv": [0.063, 0, 2.469, 1.09437], "rotation": 90, "texture": "#0"},
				"up": {"uv": [5.828, 0, 7.12488, 15.985], "rotation": 90, "texture": "#0"},
				"down": {"uv": [11.85925, 0.015, 13.17175, 16], "rotation": 90, "texture": "#0"}
			}
		},
		{
			"from": [1, 0.5, 13.75],
			"to": [15, 2, 14],
			"rotation": {"angle": 0, "axis": "y", "origin": [8, 9, 24]},
			"faces": {
				"north": {"uv": [1.798, 0, 3.454, 15.985], "rotation": 90, "texture": "#0"},
				"east": {"uv": [0.063, 0, 1.719, 0.61], "rotation": 90, "texture": "#0"},
				"south": {"uv": [1.798, 0, 3.454, 15.985], "rotation": 90, "texture": "#0"},
				"west": {"uv": [0.063, 0, 1.719, 0.61], "rotation": 90, "texture": "#0"},
				"up": {"uv": [4.3905, 0.015, 5.1405, 16], "rotation": 90, "texture": "#0"},
				"down": {"uv": [7.6405, 0, 8.3905, 15.985], "rotation": 90, "texture": "#0"}
			}
		},
		{
			"from": [1, 0.5, 2],
			"to": [15, 2, 2.25],
			"rotation": {"angle": 0, "axis": "y", "origin": [8, 9, 22]},
			"faces": {
				"north": {"uv": [1.798, 0, 3.454, 15.985], "rotation": 90, "texture": "#0"},
				"east": {"uv": [0.063, 0, 1.719, 0.61], "rotation": 90, "texture": "#0"},
				"south": {"uv": [1.798, 0, 3.454, 15.985], "rotation": 90, "texture": "#0"},
				"west": {"uv": [0.063, 0, 1.719, 0.61], "rotation": 90, "texture": "#0"},
				"up": {"uv": [7.28113, 0, 8.03112, 15.985], "rotation": 90, "texture": "#0"},
				"down": {"uv": [12.93738, 0.015, 13.68738, 16], "rotation": 90, "texture": "#0"}
			}
		},
		{
			"from": [2, 1.25, 2.25],
			"to": [2.25, 1.75, 13.75],
			"rotation": {"angle": 0, "axis": "y", "origin": [7, 1, 8]},
			"faces": {
				"north": {"uv": [0.063, 0, 1.719, 0.61], "rotation": 90, "texture": "#0"},
				"east": {"uv": [1.798, 0, 3.454, 15.985], "rotation": 90, "texture": "#0"},
				"south": {"uv": [0.063, 0, 1.719, 0.61], "rotation": 90, "texture": "#0"},
				"west": {"uv": [1.798, 0, 3.454, 15.985], "rotation": 90, "texture": "#0"},
				"up": {"uv": [5.828, 0, 6.578, 15.985], "texture": "#0"},
				"down": {"uv": [5.828, 0, 6.578, 15.985], "rotation": 180, "texture": "#0"}
			}
		},
		{
			"from": [13.75, 1.25, 2.25],
			"to": [14, 1.75, 13.75],
			"rotation": {"angle": 0, "axis": "y", "origin": [9, 1, 8]},
			"faces": {
				"north": {"uv": [0.063, 0, 1.719, 0.61], "rotation": 90, "texture": "#0"},
				"east": {"uv": [1.798, 0, 3.454, 15.985], "rotation": 90, "texture": "#0"},
				"south": {"uv": [0.063, 0, 1.719, 0.61], "rotation": 90, "texture": "#0"},
				"west": {"uv": [1.798, 0, 3.454, 15.985], "rotation": 90, "texture": "#0"},
				"up": {"uv": [5.828, 0, 6.578, 15.985], "texture": "#0"},
				"down": {"uv": [14.8905, 0, 15.6405, 15.985], "rotation": 180, "texture": "#0"}
			}
		},
		{
			"from": [1, 0.5, 14],
			"to": [15, 1.5, 15],
			"rotation": {"angle": 0, "axis": "y", "origin": [8, 9, 23]},
			"faces": {
				"north": {"uv": [1.798, 0, 3.454, 15.985], "rotation": 90, "texture": "#0"},
				"east": {"uv": [0.063, 0, 1.719, 0.61], "rotation": 90, "texture": "#0"},
				"south": {"uv": [1.798, 0, 3.454, 15.985], "rotation": 90, "texture": "#0"},
				"west": {"uv": [0.063, 0, 1.719, 0.61], "rotation": 90, "texture": "#0"},
				"up": {"uv": [0, 9, 16, 10.48438], "texture": "#0"},
				"down": {"uv": [1.65563, 10.01563, 15.65563, 12.01563], "texture": "#0"}
			}
		},
		{
			"from": [1, 0.5, 1],
			"to": [15, 1.5, 2],
			"rotation": {"angle": 0, "axis": "y", "origin": [8, 9, 23]},
			"faces": {
				"north": {"uv": [1.798, 0, 3.454, 15.985], "rotation": 90, "texture": "#0"},
				"east": {"uv": [0.063, 0, 1.719, 0.61], "rotation": 90, "texture": "#0"},
				"south": {"uv": [1.798, 0, 3.454, 15.985], "rotation": 90, "texture": "#0"},
				"west": {"uv": [0.063, 0, 1.719, 0.61], "rotation": 90, "texture": "#0"},
				"up": {"uv": [0, 7.85938, 16, 9.35938], "texture": "#0"},
				"down": {"uv": [2, 8, 16, 10], "texture": "#0"}
			}
		},
		{
			"from": [1, 0.6, 2],
			"to": [2, 1.4, 14],
			"rotation": {"angle": 0, "axis": "y", "origin": [8, 1, 8]},
			"faces": {
				"north": {"uv": [0.063, 0, 1.719, 0.61], "rotation": 90, "texture": "#0"},
				"east": {"uv": [1.798, 0, 3.454, 15.985], "rotation": 90, "texture": "#0"},
				"south": {"uv": [0.063, 0, 1.719, 0.61], "rotation": 90, "texture": "#0"},
				"west": {"uv": [1.798, 0, 3.454, 15.985], "rotation": 90, "texture": "#0"},
				"up": {"uv": [0, 7.46875, 16, 8.90625], "rotation": 90, "texture": "#0"},
				"down": {"uv": [5.828, 0, 15.828, 2], "rotation": 90, "texture": "#0"}
			}
		},
		{
			"from": [14, 0.6, 2],
			"to": [15, 1.4, 14],
			"rotation": {"angle": 0, "axis": "y", "origin": [8, 1, 8]},
			"faces": {
				"north": {"uv": [0.063, 0, 1.719, 0.61], "rotation": 90, "texture": "#0"},
				"east": {"uv": [1.798, 0, 3.454, 15.985], "rotation": 90, "texture": "#0"},
				"south": {"uv": [0.063, 0, 1.719, 0.61], "rotation": 90, "texture": "#0"},
				"west": {"uv": [1.798, 0, 3.454, 15.985], "rotation": 90, "texture": "#0"},
				"up": {"uv": [0, 7.46875, 16, 9.125], "rotation": 90, "texture": "#0"},
				"down": {"uv": [5.828, 0, 15.828, 2], "rotation": 90, "texture": "#0"}
			}
		},
		{
			"from": [2, 1.9, 2],
			"to": [14, 1.9, 14],
			"faces": {
				"up": {"uv": [0, 0, 16, 16], "texture": "#1"},
				"down": {"uv": [0, 0, 16, 16], "texture": "#1"}
			}
		},
		{
			"from": [2, 1.875, 2],
			"to": [14, 1.875, 14],
			"faces": {
				"up": {"uv": [0, 0, 16, 16], "texture": "#1"},
				"down": {"uv": [0, 0, 16, 16], "texture": "#1"}
			}
		},
		{
			"from": [2, 1.85, 2],
			"to": [14, 1.85, 14],
			"faces": {
				"up": {"uv": [0, 0, 16, 16], "texture": "#1"},
				"down": {"uv": [0, 0, 16, 16], "texture": "#1"}
			}
		},
		{
			"from": [2, 1.825, 2],
			"to": [14, 1.825, 14],
			"faces": {
				"up": {"uv": [0, 0, 16, 16], "texture": "#1"},
				"down": {"uv": [0, 0, 16, 16], "texture": "#1"}
			}
		},
		{
			"from": [2, 1.8, 2],
			"to": [14, 1.8, 14],
			"faces": {
				"up": {"uv": [0, 0, 16, 16], "texture": "#1"},
				"down": {"uv": [0, 0, 16, 16], "texture": "#1"}
			}
		},
		{
			"from": [2, 1.775, 2],
			"to": [14, 1.775, 14],
			"faces": {
				"up": {"uv": [0, 0, 16, 16], "texture": "#1"},
				"down": {"uv": [0, 0, 16, 16], "texture": "#1"}
			}
		},
		{
			"from": [7.15, 0, 1.15],
			"to": [8.85, 2, 1.5],
			"faces": {
				"north": {"uv": [12.46875, 14.0625, 13.96875, 15.5625], "texture": "#0"},
				"east": {"uv": [12.46875, 14.0625, 13.96875, 15.5625], "texture": "#0"},
				"south": {"uv": [12.46875, 14.0625, 13.96875, 15.5625], "texture": "#0"},
				"west": {"uv": [12.46875, 14.0625, 13.96875, 15.5625], "texture": "#0"},
				"up": {"uv": [12.46875, 14.0625, 13.96875, 15.5625], "texture": "#0"},
				"down": {"uv": [12.46875, 14.0625, 13.96875, 15.5625], "texture": "#0"}
			}
		},
		{
			"from": [7.25, 1.95, 1.25],
			"to": [8.75, 2.05, 1.75],
			"faces": {
				"north": {"uv": [12.46875, 14.0625, 13.96875, 15.5625], "texture": "#0"},
				"east": {"uv": [12.46875, 14.0625, 13.96875, 15.5625], "texture": "#0"},
				"south": {"uv": [12.46875, 14.0625, 13.96875, 15.5625], "texture": "#0"},
				"west": {"uv": [12.46875, 14.0625, 13.96875, 15.5625], "texture": "#0"},
				"up": {"uv": [11.5, 14.125, 13.96875, 15.5625], "texture": "#0"},
				"down": {"uv": [12.46875, 14.0625, 13.96875, 15.5625], "texture": "#0"}
			}
		},
		{
			"from": [7.25, -0.05, 1.25],
			"to": [8.75, 0.05, 1.75],
			"faces": {
				"north": {"uv": [12.46875, 14.0625, 13.96875, 15.5625], "texture": "#0"},
				"east": {"uv": [12.46875, 14.0625, 13.96875, 15.5625], "texture": "#0"},
				"south": {"uv": [12.46875, 14.0625, 13.96875, 15.5625], "texture": "#0"},
				"west": {"uv": [12.46875, 14.0625, 13.96875, 15.5625], "texture": "#0"},
				"up": {"uv": [12.46875, 14.0625, 13.96875, 15.5625], "texture": "#0"},
				"down": {"uv": [12.46875, 14.0625, 13.96875, 15.5625], "texture": "#0"}
			}
		}
	],
	"display": {
		"thirdperson_righthand": {
			"rotation": [75, 45, 0],
			"translation": [0, 2.5, 1.75],
			"scale": [0.375, 0.375, 0.375]
		},
		"thirdperson_lefthand": {
			"rotation": [75, 45, 0],
			"translation": [0, 2.5, 1.75],
			"scale": [0.375, 0.375, 0.375]
		},
		"firstperson_righthand": {
			"rotation": [45, 45, 0],
			"translation": [0, 0.75, 0],
			"scale": [0.8, 0.8, 0.8]
		},
		"firstperson_lefthand": {
			"rotation": [45, 45, 0],
			"translation": [0, 0.75, 0],
			"scale": [0.8, 0.8, 0.8]
		},
		"ground": {
			"translation": [0, 3, 0],
			"scale": [0.5, 0.5, 0.5]
		},
		"gui": {
			"rotation": [30, 225, 0],
			"translation": [0, 4, 0],
			"scale": [0.625, 0.625, 0.625]
		},
		"fixed": {
			"rotation": [-90, 0, 0],
			"translation": [0, 0, -6.5],
			"scale": [0.8, 0.8, 0.8]
		}
	}
}